LabelmeUtils/LabelmePayload.py
LabelmeUtils/ShapeIterator.py
LabelmeUtils/Shapes.py
LabelmeUtils/__init__.py
LabelmeUtils-0.0.14.dist-info/LICENSE.txt
LabelmeUtils-0.0.14.dist-info/METADATA
LabelmeUtils-0.0.14.dist-info/WHEEL
LabelmeUtils-0.0.14.dist-info/top_level.txt
LabelmeUtils-0.0.14.dist-info/RECORD
