Metadata-Version: 2.1
Name: LabelmeUtils
Version: 0.0.14
Summary: Tool to decode labelme json payloads
Home-page: https://gitlab.com/futurefragment-pub/labelme-utils
Author: sholto
Author-email: sholto@futurefragment.com
License: MIT
Platform: UNKNOWN
Requires-Dist: Pillow
